restful_dnspod_log/__init__.py
restful_dnspod_log/main.py
restful_dnspod_log-1.0.2.dist-info/METADATA
restful_dnspod_log-1.0.2.dist-info/WHEEL
restful_dnspod_log-1.0.2.dist-info/top_level.txt
restful_dnspod_log-1.0.2.dist-info/RECORD
