Metadata-Version: 2.1
Name: restful-dnspod-log
Version: 1.0.2
Summary: return the log for dns resolution
Home-page: https://github.com/hanyan007/RESTful_DNSPOD_LOG.git
Author: hanyan_news
Author-email: hanyan0572@gmail.com
License: BSD License
Project-URL: Source, https://github.com/hanyan007/RESTful_DNSPOD_LOG.git
Platform: all
Classifier: Intended Audience :: Developers
Classifier: Operating System :: OS Independent
Classifier: Natural Language :: Chinese (Simplified)
Classifier: Programming Language :: Python
Classifier: Programming Language :: Python :: 2
Classifier: Programming Language :: Python :: 2.7
Classifier: Programming Language :: Python :: 3
Classifier: Programming Language :: Python :: 3.5
Classifier: Programming Language :: Python :: 3.6
Classifier: Programming Language :: Python :: 3.7
Classifier: Programming Language :: Python :: 3.8
Classifier: Topic :: Software Development :: Libraries
Requires-Dist: package-tea-hanyan (==1.0.4)
Requires-Dist: dnspod-domain-log (==1.0.2)
Requires-Dist: package-tea-one (==1.0.0)
